dataset/__init__.py
dataset/chunked.py
dataset/database.py
dataset/table.py
dataset/types.py
dataset/util.py
sqla_dataset-1.0.0.dist-info/licenses/LICENSE.txt
sqla_dataset-1.0.0.dist-info/METADATA
sqla_dataset-1.0.0.dist-info/WHEEL
sqla_dataset-1.0.0.dist-info/top_level.txt
sqla_dataset-1.0.0.dist-info/RECORD
